paywhirl/__init__.py
paywhirl/paywhirl.py
paywhirl-1.2.dist-info/LICENSE
paywhirl-1.2.dist-info/METADATA
paywhirl-1.2.dist-info/WHEEL
paywhirl-1.2.dist-info/top_level.txt
paywhirl-1.2.dist-info/RECORD
