Metadata-Version: 2.1
Name: paywhirl
Version: 1.2
Summary: Python client for PayWhirl API
Home-page: https://github.com/paywhirl/python-pwclient
Author: PayWhirl
Author-email: developer@paywhirl.com
License: UNKNOWN
Platform: UNKNOWN
Classifier: Programming Language :: Python :: 3
Classifier: License :: OSI Approved :: MIT License
Classifier: Operating System :: OS Independent
Requires-Python: >=3.5
